find_keyword.cpython-312-darwin.so
find_keyword_xtvu-7.5.dist-info/METADATA
find_keyword_xtvu-7.5.dist-info/WHEEL
find_keyword_xtvu-7.5.dist-info/top_level.txt
find_keyword_xtvu-7.5.dist-info/RECORD
