Metadata-Version: 2.1
Name: find_keyword_xtvu
Version: 7.5
Summary: A package to find keywords in .pdf, .docx, .odt, and .rtf files
Author: Xuan Tung VU
Classifier: Programming Language :: Python :: 3
Classifier: Programming Language :: Cython
Classifier: Operating System :: OS Independent
Classifier: License :: OSI Approved :: MIT License
Classifier: Development Status :: 4 - Beta
Classifier: Intended Audience :: Developers
Classifier: Topic :: Software Development :: Libraries :: Python Modules
Requires-Python: >=3.10
